[{"numberOfPages":457,"title":"En liftares guide till Galaxen","author":"Douglas Adams","purchaseDate":"1981-01-01"},{"numberOfPages":376,"title":"Att välja glädje","author":"Kay Pollack","purchaseDate":"2001-01-01"},{"numberOfPages":6578648,"title":"Bibeln","author":"Anonym","purchaseDate":"2000-01-01"},{"numberOfPages":5,"title":"Hej","author":"Lena","purchaseDate":"2022-10-21"},{"numberOfPages":245,"title":"kljdnf","author":"asfkln","purchaseDate":"2022-10-21"},{"numberOfPages":4,"title":"sdg","author":"sdg","purchaseDate":"2022-10-21"},{"numberOfPages":4,"title":"kjsdng","author":"kjnd","purchaseDate":"2022-10-21"},{"numberOfPages":8745,"title":"hejhej","author":"arne","purchaseDate":"2022-10-21"},{"numberOfPages":1,"title":"tjena","author":"lena","purchaseDate":"2022-10-21"},{"numberOfPages":1,"title":"bok1","author":"titel1","purchaseDate":"2022-10-21"},{"numberOfPages":2,"title":"titel2","author":"lena2","purchaseDate":"2022-10-21"},{"numberOfPages":3,"title":"titel","author":"lena","purchaseDate":"2022-10-21"},{"numberOfPages":4,"title":"kjndgs","author":"sdfgljkns","purchaseDate":"2022-10-21"},{"numberOfPages":56,"title":"test","author":"testsson","purchaseDate":"2022-10-21"},{"numberOfPages":23,"title":"hejhejhej","author":"författare","purchaseDate":"2022-10-21"},{"numberOfPages":5,"title":"lkmdg","author":"jkadnfkj","purchaseDate":"2022-10-21"}]